{
  "culture": "vi",
  "texts": {
    "TableFilter": "Bộ lọc",
    "Menu:Hrm": "Nhân sự",
    "MyAccount": "Tài khoản của tôi",
    "SamplePageMessage": "Trang mẫu cho mô-đun Hrm",
    "Menu:Department": "Phòng ban",
    "Department": "Phòng ban",
    "DepartmentId": "ID",
    "DepartmentName": "Tên phòng",
    "DepartmentOwnerId": "Trưởng phòng",
    "DepartmentParentId": "Khối phòng",
    "ownerName": "Trưởng phòng",
    "parentName": "Khối phòng",
    "OwnerName": "Trưởng phòng",
    "ParentName": "Khối phòng",
    "DepartmentDeletionConfirmationMessage": "Bạn có chắc chắn muốn xóa phòng ban {0}?",
    "CreateDepartment": "Thêm phòng ban",
    "EditDepartment": "Sửa phòng ban",
    "Menu:Employee": "Nhân viên ",
    "Employee": "Nhân viên",
    "EmployeeName": "Tên nhân viên",
    "EmployeeOtherName": "Tên khác",
    "EmployeeHrmUserId": "User",
    "HrmUserName": "Tên đăng nhập",
    "HrmContactName": "Tên liên lạc",
    "HrmUser": "Tên đăng nhập",
    "HrmContact": "Tên liên lạc",
    "SelectHrmUser": "Chọn tên đăng nhập",
    "SelectHrmContact": "Chọn liên lạc",
    "SelectDepartment": "Chọn phòng ban",
    "EmployeeContactId": "EmployeeContactId",
    "EmployeeDepartmentId": "EmployeeDepartmentId",
    "EmployeeStatus": "Trạng thái",
    "OtherName": "Tên khác",
    "Status": "Trạng thái",
    "Active": "Hoạt động",
    "NumberTimeOf": "Số phép nghỉ",
    "EmployeeActive": "Hoạt động",
    "EmployeeNumberTimeOf": "Số phép nghỉ",
    "CreateEmployee": "Tạo nhân viên",
    "EditEmployee": "Sửa nhân viên",
    "EmployeeDeletionConfirmationMessage": "Bạn có chắc chắn muốn xóa nhân viên này {0}?",
    "Menu:HRNeed": "Nhu cầu nhân sự",
    "Menu:RecruitmentPlan": "Kế hoạch tuyển dụng",
    "Menu:Candidate": "Ứng viên",
    "Menu:1stInterview": "Phỏng vấn lần 1",
    "Menu:2stInterview": "Phỏng vấn lần 1",
    "Menu:TrailWork": "Thử việc",
    "Menu:Recruitment": "Tuyển dụng",
    "Menu:DayOffs": "Xin nghỉ",
    "Menu:Shift": "Ca làm việc",
    "Menu:AllApplicationForLeave": "Tất cả đơn xin nghỉ",
    "Menu:TakeALeaveOfAbsence": "Xin nghỉ",
    "Menu:PleaseComeLateComeBackEarly": "Xin đi muộn về sớm",
    "Menu:PleaseComeLateComeBackEarlyEveryYear": "Xin đi muộn về sớm thường niên",
    "Menu:ApproveApplication": "Duyệt đơn",
    "Menu:SetPublicHolidays": "Thiết lập ngày nghỉ chung",
    "Menu:Timekeeping": "Chấm công",
    "Menu:TimekeepingByMonth": "Chấm công theo tháng",
    "Menu:TimekeepingByDay": "Chấm công theo ngày",
    "Menu:ApproveTimeKeeping": "Xác nhận chấm công",
    "Menu:SetShift" : "Thiết lập ca làm việc",
    "Menu:ConfigurationTimeKeeping": "Cấu hình chấm công",
    "Menu:Payroll": "Bảng lương",
    "Menu:Contract": "Hợp đồng",
    "Menu:Insurance": "Bảo hiểm",
    "CustomColumn": "Sửa cột",
    "Attendent": "Chấm công theo ngày",
    "CreateAttendent": "Thêm mới chấm công theo ngày",
    "EditAttendent": "Sửa chấm công theo ngày",
    "Date": "Ngày",
    "MissingIn": "Quên chấm vào",
    "MissingOut": "Quên chấm ra",
    "Holiday": "Ngày nghỉ",
    "CreateHoliday": "Thêm ngày nghỉ",
    "EditHoliday": "Sửa ngày nghỉ",
    "shiftName": "Ca làm việc",
    "DayofWeek": "Thứ trong tuần",
    "Type": "Loại ngày nghỉ",
    "IsPaid": "Nghỉ có lương",
    "PaidPercent": "Phần trăm hưởng lương",
    "CompesatoryDay" : "Ngày làm bù",
    "IsFullDay" : "Nghỉ cả ngày",
    "CreateShift": "Thêm ca làm việc",
    "EditShift": "Sửa ca làm việc",
    "Start": "Bắt đầu",
    "End":"Kết thúc",
    "SelectShift": "Chọn ca làm việc",
    "Permission:ConfigSalary": "Cấu hình lương bổng",
    "Menu:ConfigSalary": "Cấu hình lương bổng",
    "ConfigSalary": "Cấu hình lương bổng",
    "ConfigSalaryName": "Tên cấu hình",
    "ConfigSalaryIsDefault": "Tính lương mặc định",
    "CreateConfigSalary": "Tạo cấu hình",
    "EditConfigSalary": "Sửa cấu hình",
    "ConfigSalaryDeletionConfirmationMessage": "Bạn chắc chắn xóa cấu hình này {0}?",
    "Permission:ConfigSalaryColumn": "Cấu hình từng cột lương",
    "Menu:ConfigSalaryColumn": "Cấu hình từng cột lương",
    "ConfigSalaryColumn": "Cấu hình từng cột lương",
    "ConfigSalaryColumnName": "Tên cột",
    "ConfigSalaryColumnCode": "Mã số cột",
    "ConfigSalaryColumnRecipe": "Công thức",
    "CreateConfigSalaryColumn": "Tạo cột lương mới",
    "EditConfigSalaryColumn": "Sửa cột lương",
    "ConfigSalaryColumnDeletionConfirmationMessage": "Bạn có chắc chắn xóa cột lương này {0}?",
    "Permission:SalaryForMonth": "Bảng lương theo tháng",
    "Menu:SalaryForMonth": "Bảng lương theo tháng",
    "SalaryForMonth": "Bảng lương theo tháng",
    "SalaryForMonthMonthAndYear": "Tháng",
    "SalaryForMonthStatus": "Tình trạng",
    "CreateSalaryForMonth": "Tạo bảng lương theo tháng",
    "EditSalaryForMonth": "Sửa bảng lương theo tháng",
    "SalaryForMonthDeletionConfirmationMessage": "Bạn có chắc chắn xóa bảng lương theo tháng đã chọn {0}?",
    "Permission:Salary": "Bảng lương",
    "Menu:Salary": "Bảng lương",
    "Salary": "Bảng lương",
    "SalaryEmployeeId": "Nhân viên",
    "SalaryDetail": "Chi tiết bảng lương",
    "CreateSalary": "Tạo bảng lương",
    "EditSalary": "Sửa bảng lương",
    "TypeContractEmployeeName":"Loại hợp đồng",
    "Menu:ContractEmployee": "Cấu hình hợp đồng",
    "Menu:TimeContract":"Cấu hình thời hạn hợp đồng",
    "Menu:TypeContractEmployee": "Cấu hình loại hợp đồng",
    "Menu:Company":"Công ty",
    "SelectTimeContract": "Chọn thời hạn hợp đồng",
    "SelectTypeContractEmployee": " Chọn loại thời hạn hợp đồng",
    "SelectCompany":"Chọn công ty",
    "SelectEmployee":"Chọn nhân viên",
    "TimeContract": "Thời hạn hợp đồng",
    "TimeContractName":"Thời hạn hợp đồng",
    "TimeContractDescription": "Mô tả hợp đồng",
    "TypeContractEmployee": "Loại hợp đồng",
    "TypeContractNameEmployeeName":"Loại hợp đồng",
    "TypeContractEmployeeDescription": "Mô tả loại hợp đồng",
    "timeContractName": "Thời hạn hợp đồng",
    "typeContractEmployeeName":"Loại hợp đồng",
    "companyName": "Công ty",
    "employeeName":"Tên nhân viên",
    "ContractEmployeeStartDate": "Ngày hiệu lực",
    "ContractEmployeeEndDate":"Ngày hết hạn",
    "ContractEmployeeHardSalary": "Lương cơ bản",
    "ContractEmployeeSalaryWithSS":"Lương đóng bảo hiểm",
    "ContractEmployeeSSperSalary": "Tỷ lệ hưởng lương",
    "CreateContractEmployee": "Tạo hợp đồng",
    "ContractEmployee": "Hợp đồng nhân viên",
    "CreateTimeContract": "Tạo thời hạn hợp đồng",
    "CreateTypeContractEmployee": "Tạo loại hợp đồng",
    "CompanyName": "Tên công ty",
    "CompanyDescription": "Mô tả công ty",
    "Company": "Công ty",
    "CreateCompany": "Thêm công ty",
    "SuccessfullyEditOwner!": "Cập nhật trưởng phòng thành công !",
    "EditOwnerHistory" : "Lịch sử cập nhật trưởng phòng",
    "Username": "Người tạo",
    "ChangeTime": "Thời gian cập nhật",
    "Change": "Thay đổi",
    "newOwnerName": "Trưởng phòng mới",
    "SuccessCreated": "Thêm thành công",
    "SuccessDeleted" : "Xoá thành công",
    "ErrorDelete": "Xoá thất bại",
    "Description": "Mô tả hợp đồng",
    "ShiftName": "Tên ca làm việc",
    "SocialSecurityForEnterprise":"Doanh nghiệp đóng",
    "SocialSecurityForEmployee":"Nhân viên đóng",
    "TotalMoney":"Tổng tiền",
    "SocialSecurity":"Bảo hiểm xã hội",
    "CreateSocialSecurity":"Tạo Bảo hiểm xã hội",
    "Menu:SocialSecurity":"Bảo hiểm xã hội",
    "ConfigSocialSecurity": "Cấu hình bảo hiểm xã hội",
    "Menu:ConfigSocialSecurity": "Cấu hình bảo hiểm xã hội",
    "CreateConfigSocialSecurity": "Tạo cấu hình bảo hiểm xã hội",
    "ConfigSocialSecurityName": "Tên bảo hiểm",
    "ConfigSocialSecurityDetail": "Chi tiết cấu hình",
    "ConfigSocialSecurityPercentForEnterprise": "Hệ số doanh nghiệp đóng",
    "ConfigSocialSecurityPercentForEmployee": "Hệ số người lao động đóng",
    "ContractEmployeeTimeContractId": "Hợp đồng nhân viên",
    "ContractEmployeeTypeContractEmployeeId":"Loại hợp đồng",
    "ContractEmployeeCompanyId": "Công ty",
    "ContractEmployeeEmployeeId":"Tên nhân viên",
    "HardSalary": "Lương cơ bản",
    "SalaryWithSS":"Lương đóng BH",
    "SSperSalary": "Tỷ lệ hưởng lương",
    "StartDate": "Ngày hiệu lực",
    "EndDate": "Ngày hết hạn",
    "Department:ViewDetailDepartment": "Xem chi tiết",
    "Department Information": "Xem Phòng Ban",
    "PhoneNumber": "Số điện thoại",
    "EmployeeHrmUserName": "Tên đăng nhập",
    "EmployeeHrmContactName":"Tên liên lạc",
    "EmployeeDepartmentName": "Tên phòng",
    "DepartmentOwnerName": "Trưởng phòng",
    "DepartmentParentName":"Khối phòng",
    "EmployeeContactBirthDay": "Ngày sinh",
    "EmployeeContactGender":"Giới tính",
    "EmployeeContactEmail": "Email",
    "EmployeeContactPhoneNumber":"Số điện thoại",
    "Name": "Tên nhân viên",
    "Menu:Category": "Danh mục",
    "Category":"Danh mục",
    "CategoryName": "Tên",
    "TypeCategory":"Phân loại",
    "CategoryTypeCategory":"Phân loại",
    "CreateCategory": "Tạo mới danh mục",
    "EditCategory":"Cập nhật danh mục",
    "Qualification": "Trình độ chuyên môn",
    "JobPosition": "Vị trí công việc",
    "ReasonForLeave": "Lý do xin nghỉ",
    "Qualification:0" :"Trình độ chuyên môn",
    "Qualification:1" :"Vị trí công việc",
    "Qualification:2" :"Lý do xin nghỉ",
    "EmployeeStatus:0": "Online",
    "EmployeeStatus:1": "Offline",
    "EmployeeActive:false": "Không hoạt động",
    "EmployeeActive:true": "Hoạt động",
    "ForEnterprise": "Doanh nghiệp đóng",
    "ForEmployee": "Nhân viên đóng",
    "Detail": "Chi tiết cấu hình",
    "PercentForEnterprise":"Hệ số doanh nghiệp đóng",
    "PercentForEmployee": "Hệ số nhân viên đóng",
    "EditContractEmployee": "Cập nhật hợp đồng",
    "NoOption": "Không lựa chọn",
    "EditOwner": "Cập nhật trưởng phòng",
    "isPaid:false": "Không lương",
    "isPaid:true": "Có lương",
    "isFullDay:true" : "Nghỉ cả ngày",
    "isFullDay:false" : "Không nghỉ cả ngày",
    "CheckIn": "Vào",
    "CheckOut": "Ra",
    "TypeLine" : "Loại",
    "SalaryForMonthName" : "Tên bảng lương theo tháng",
    "TimeStartCheckin": "Thời gian bắt đầu chấm công ",
    "TimeStopCheckout": "Thời gian kết thúc chấm công",
    "Shift": "Ca làm việc",
    "ShiftDeletionConfirmationMessage": "Bạn có chắc chắn muốn xóa ca làm việc {0}?",
    "ApproverDeletionConfirmationMessage": "Bạn có chắc chắn muốn xóa duyệt đơn {0}?",
    "AttendentDeletionConfirmationMessage": "Bạn có chắc chắn muốn xóa chấm công {0}?",
    "AttendentLineDeletionConfirmationMessage": "Bạn có chắc chắn muốn xóa chấm công {0}?",
    "gender:0": "Nam",
    "gender:1": "Nữ",
    "gender:2": "Khác",
    "Male": "Nam",
    "Female": "Nữ",
    "Gender": "Giới tính",
    "BirthDay": "Ngày sinh",
    "ContactAddress": "Địa chỉ",
    "ContactPhoneNumber": "Số điện thoại",
    "ContactEmail": "Email",
    "ContactActive": "Trạng thái",
    "ContactBirthday": "Ngày sinh",
    "Menu:Contact": "Liên Lạc" ,
    "ContractName": "Tên Hợp Đồng",
    "ContactName": "Tên liên lạc",
    "ContactGender": "Giới Tính",
    "Menu:Attendent": "Chấm Công",
    "Menu:EmployeeHistory": "Tiểu Sử Nhân Viên",
    "Menu:AttendentLine" : "Dòng Chấm Công",
    "Menu:AttendentForMonth": "Chấm Công theo Tháng",
    "ContractEmployeeName": "Họ Tên ",
    "ContractDateSign": "Ngày Kí Hợp Đồng",
    "ContractCoefficientSalary": "Hệ số lương",
    "CoefficientSalary": "Hệ số lương",
    "CreateContact": "Tạo liên lạc",
    "CreateContract": "Tạo Hợp đồng",
    "ShiftStart": "Thời gian bắt đầu ca",
    "ShiftEnd" : "Thơi gian tan ca",
    "ShiftTimeStartCheckIn":"Thời gian bắt đầu chấm công",
    "ShiftTimeStopCheckout":"Thời gian Kết Thúc chấm công",
    "ContractSignDate": "Ngày kí Hợp đồng",
    "ContractEmployeeId": "Tên nhân viên",
    "ContractTimeContract" : "Thời hạn hợp đồng",
    "ContactBirthDay": "Ngày sinh",
    "AttendentForMonthMonth" : "Tháng",
    "TotalSalary": "Tổng lương",
    "SalaryEmployeeName" : "Tên nhân viên",
    "TimeSalary": "Tháng",
    "SalaryDateSign" : "Tổng lương",
    "Month": "Tháng ",
    "Count": "Số công",
    "AttendentForMonthEmployeeName" : "Tên nhân viên",
    "EmployeeHistoryStart": "Ngày bắt đầu ",
    "EmployeeHistoryEnd": "Ngày kết thúc",
    "EmployeeHistoryJobPosition": "Vị trí làm việc",
    "EmployeeHistoryOrganization": "Công ty đã làm việc",
    "EmployeeHistoryDescription": "Mô tả",
    "Organization": "Công ty",
    "EmployeeHistoryEmployeeName": "Tên nhân viên",
    "CreateEmployeeHistory": "Tạo mới",
    "Contact": "Liên hệ",
    "AttendentForMonth": "Chấm công theo tháng",
    "Contract": "Hợp đồng",
    "EmployeeHistory": "Tiểu sử nhân viên",
    "active:true": "Hoạt động",
    "active:false": "Không hoạt động",
    "timeContract:0": "6 tháng",
    "timeContract:1": "1 năm",
    "timeContract:2": "3 năm",
    "WorkHistory": "Quá trình công tác",
    "EmployeeCV" : "Quá trình công tác",
    "NoWorkHistory" : "Chưa có",
    "EditEmployeeDepartment": "Điều chuyển nhân sự",
    "SalaryAttendentForMonthId" : "Tháng",
    "SalaryAttendentForMonthMonth" : "Tháng",
    "AttendentForMonthCount" : "Tổng công",
    "CreateManyAttendentForMonth" : "Tạo tất cả chấm công theo tháng",
    "CreateAttendentForMonth" : "Tạo mới",
    "CreateManySalary" : "Tạo tất cả bảng lương theo tháng",
    "EmmployeeHistoryStart": "Bắt đầu",
    "EmmployeeHistoryEnd":"Kết thúc",
    "EmmployeeHistoryOrganization":  "Công ty",
    "EmmployeeHistoryDescription" : "Mô tả",
    "EditAttendentForMonth" : "Sửa chấm công theo tháng",
    "ContacPhoneNumber" : "Số điện thoại",
    "EditContact" : "Sửa liên lạc",
    "ExportAllAttendentForMonthModal" : "Xuất tất cả chấm công theo tháng",
    "CreateAllAttendentForMonthInMonth" : "Xuất tất cả chấm công theo tháng",
    "ExportSalaryForMonth" : "Xuất tất cả bảng lương theo tháng",
    "ExportSalaryForMonthForDepartment" : "Xuất bảng lương theo phòng ban",
    "IndexOfRecord" : "STT",
    "employeePosition:4" : "Nhân viên",
    "employeePosition:3" : "Phó phòng",
    "employeePosition:2" : "Trưởng phòng",
    "employeePosition:1" : "Phó giám đốc",
    "employeePosition:0" : "Giám đốc"
    
    
    
    
    
  }
} 